{
	"animations": [
		{
			"loop": false,
			"offsets": [
				0,
				0
			],
			"anim": "idle",
			"fps": 24,
			"name": "idle",
			"indices": []
		},
		{
			"loop": false,
			"offsets": [
				235,
				7
			],
			"anim": "singLEFT",
			"fps": 24,
			"name": "left",
			"indices": []
		},
		{
			"loop": false,
			"offsets": [
				-56,
				-23
			],
			"anim": "singDOWN",
			"fps": 24,
			"name": "down",
			"indices": []
		},
		{
			"loop": false,
			"offsets": [
				88,
				28
			],
			"anim": "singUP",
			"fps": 24,
			"name": "up",
			"indices": []
		},
		{
			"loop": false,
			"offsets": [
				-75,
				0
			],
			"anim": "singRIGHT",
			"fps": 24,
			"name": "right",
			"indices": []
		}
	],
	"no_antialiasing": false,
	"image": "characters/boy",
	"position": [
		40,
		-30
	],
	"healthicon": "boy",
	"flip_x": false,
	"healthbar_colors": [
		32,
		0,
		216
	],
	"camera_position": [
		0,
		0
	],
	"sing_duration": 6.1,
	"scale": 1.5
}